{
  "metrics": {
    "requests": {
      "values": [
        28,
        28,
        28,
        28,
        28,
        null
      ],
      "sum": 140,
      "min": 28,
      "max": 28,
      "median": 28,
      "average": 28
    },
    "gzipRequests": {
      "values": [
        2,
        2,
        2,
        2,
        2,
        null
      ],
      "sum": 10,
      "min": 2,
      "max": 2,
      "median": 2,
      "average": 2
    },
    "postRequests": {
      "values": [
        0,
        0,
        0,
        0,
        0,
        null
      ],
      "sum": 0,
      "min": 0,
      "max": 0,
      "median": 0,
      "average": 0
    },
    "httpsRequests": {
      "values": [
        0,
        0,
        0,
        0,
        0,
        null
      ],
      "sum": 0,
      "min": 0,
      "max": 0,
      "median": 0,
      "average": 0
    },
    "notFound": {
      "values": [
        0,
        0,
        0,
        0,
        0,
        null
      ],
      "sum": 0,
      "min": 0,
      "max": 0,
      "median": 0,
      "average": 0
    },
    "timeToFirstByte": {
      "values": [
        442,
        474,
        496,
        513,
        550,
        null
      ],
      "sum": 2475,
      "min": 442,
      "max": 550,
      "median": 496,
      "average": 495
    },
    "timeToLastByte": {
      "values": [
        455,
        488,
        511,
        529,
        563,
        null
      ],
      "sum": 2546,
      "min": 455,
      "max": 563,
      "median": 511,
      "average": 509.2
    },
    "bodySize": {
      "values": [
        54144,
        71675,
        75107,
        75830,
        111960,
        null
      ],
      "sum": 388716,
      "min": 54144,
      "max": 111960,
      "median": 75107,
      "average": 77743.2
    },
    "contentLength": {
      "values": [
        274226,
        288123,
        298221,
        299432,
        300850,
        null
      ],
      "sum": 1460852,
      "min": 274226,
      "max": 300850,
      "median": 298221,
      "average": 292170.4
    },
    "httpTrafficCompleted": {
      "values": [
        3378,
        3552,
        3591,
        3826,
        4252,
        null
      ],
      "sum": 18599,
      "min": 3378,
      "max": 4252,
      "median": 3591,
      "average": 3719.8
    },
    "ajaxRequests": {
      "values": [
        0,
        0,
        0,
        0,
        0,
        null
      ],
      "sum": 0,
      "min": 0,
      "max": 0,
      "median": 0,
      "average": 0
    },
    "htmlCount": {
      "values": [
        1,
        1,
        1,
        1,
        1,
        null
      ],
      "sum": 5,
      "min": 1,
      "max": 1,
      "median": 1,
      "average": 1
    },
    "htmlSize": {
      "values": [
        10059,
        10059,
        10059,
        10059,
        10059,
        null
      ],
      "sum": 50295,
      "min": 10059,
      "max": 10059,
      "median": 10059,
      "average": 10059
    },
    "cssCount": {
      "values": [
        2,
        2,
        2,
        2,
        2,
        null
      ],
      "sum": 10,
      "min": 2,
      "max": 2,
      "median": 2,
      "average": 2
    },
    "cssSize": {
      "values": [
        95600,
        95600,
        95600,
        95600,
        95600,
        null
      ],
      "sum": 478000,
      "min": 95600,
      "max": 95600,
      "median": 95600,
      "average": 95600
    },
    "jsCount": {
      "values": [
        4,
        4,
        4,
        4,
        4,
        null
      ],
      "sum": 20,
      "min": 4,
      "max": 4,
      "median": 4,
      "average": 4
    },
    "jsSize": {
      "values": [
        28523,
        28659,
        28973,
        29941,
        41320,
        null
      ],
      "sum": 157416,
      "min": 28523,
      "max": 41320,
      "median": 28973,
      "average": 31483.2
    },
    "jsonCount": {
      "values": [
        0,
        0,
        0,
        0,
        0,
        null
      ],
      "sum": 0,
      "min": 0,
      "max": 0,
      "median": 0,
      "average": 0
    },
    "jsonSize": {
      "values": [
        0,
        0,
        0,
        0,
        0,
        null
      ],
      "sum": 0,
      "min": 0,
      "max": 0,
      "median": 0,
      "average": 0
    },
    "imageCount": {
      "values": [
        21,
        21,
        21,
        21,
        21,
        null
      ],
      "sum": 105,
      "min": 21,
      "max": 21,
      "median": 21,
      "average": 21
    },
    "imageSize": {
      "values": [
        139594,
        141144,
        163903,
        165250,
        165250,
        null
      ],
      "sum": 775141,
      "min": 139594,
      "max": 165250,
      "median": 163903,
      "average": 155028.2
    },
    "webfontCount": {
      "values": [
        0,
        0,
        0,
        0,
        0,
        null
      ],
      "sum": 0,
      "min": 0,
      "max": 0,
      "median": 0,
      "average": 0
    },
    "webfontSize": {
      "values": [
        0,
        0,
        0,
        0,
        0,
        null
      ],
      "sum": 0,
      "min": 0,
      "max": 0,
      "median": 0,
      "average": 0
    },
    "base64Count": {
      "values": [
        0,
        0,
        0,
        0,
        0,
        null
      ],
      "sum": 0,
      "min": 0,
      "max": 0,
      "median": 0,
      "average": 0
    },
    "base64Size": {
      "values": [
        0,
        0,
        0,
        0,
        0,
        null
      ],
      "sum": 0,
      "min": 0,
      "max": 0,
      "median": 0,
      "average": 0
    },
    "otherCount": {
      "values": [
        0,
        0,
        0,
        0,
        0,
        null
      ],
      "sum": 0,
      "min": 0,
      "max": 0,
      "median": 0,
      "average": 0
    },
    "otherSize": {
      "values": [
        0,
        0,
        0,
        0,
        0,
        null
      ],
      "sum": 0,
      "min": 0,
      "max": 0,
      "median": 0,
      "average": 0
    },
    "cacheHits": {
      "values": [
        4,
        4,
        4,
        4,
        4,
        null
      ],
      "sum": 20,
      "min": 4,
      "max": 4,
      "median": 4,
      "average": 4
    },
    "cacheMisses": {
      "values": [
        0,
        0,
        0,
        0,
        0,
        null
      ],
      "sum": 0,
      "min": 0,
      "max": 0,
      "median": 0,
      "average": 0
    },
    "cachePasses": {
      "values": [
        0,
        0,
        0,
        0,
        0,
        null
      ],
      "sum": 0,
      "min": 0,
      "max": 0,
      "median": 0,
      "average": 0
    },
    "cachingNotSpecified": {
      "values": [
        4,
        4,
        4,
        4,
        4,
        null
      ],
      "sum": 20,
      "min": 4,
      "max": 4,
      "median": 4,
      "average": 4
    },
    "cachingTooShort": {
      "values": [
        2,
        2,
        2,
        2,
        2,
        null
      ],
      "sum": 10,
      "min": 2,
      "max": 2,
      "median": 2,
      "average": 2
    },
    "cachingDisabled": {
      "values": [
        20,
        20,
        20,
        20,
        20,
        null
      ],
      "sum": 100,
      "min": 20,
      "max": 20,
      "median": 20,
      "average": 20
    },
    "oldCachingHeaders": {
      "values": [
        5,
        5,
        5,
        5,
        5,
        null
      ],
      "sum": 25,
      "min": 5,
      "max": 5,
      "median": 5,
      "average": 5
    },
    "consoleMessages": {
      "values": [
        0,
        0,
        0,
        0,
        0,
        null
      ],
      "sum": 0,
      "min": 0,
      "max": 0,
      "median": 0,
      "average": 0
    },
    "domains": {
      "values": [
        5,
        5,
        5,
        5,
        5,
        null
      ],
      "sum": 25,
      "min": 5,
      "max": 5,
      "median": 5,
      "average": 5
    },
    "maxRequestsPerDomain": {
      "values": [
        21,
        21,
        21,
        21,
        21,
        null
      ],
      "sum": 105,
      "min": 21,
      "max": 21,
      "median": 21,
      "average": 21
    },
    "medianRequestsPerDomain": {
      "values": [
        2,
        2,
        2,
        2,
        2,
        null
      ],
      "sum": 10,
      "min": 2,
      "max": 2,
      "median": 2,
      "average": 2
    },
    "DOMqueries": {
      "values": [
        7,
        7,
        7,
        7,
        7,
        null
      ],
      "sum": 35,
      "min": 7,
      "max": 7,
      "median": 7,
      "average": 7
    },
    "DOMqueriesById": {
      "values": [
        4,
        4,
        4,
        4,
        4,
        null
      ],
      "sum": 20,
      "min": 4,
      "max": 4,
      "median": 4,
      "average": 4
    },
    "DOMqueriesByClassName": {
      "values": [
        0,
        0,
        0,
        0,
        0,
        null
      ],
      "sum": 0,
      "min": 0,
      "max": 0,
      "median": 0,
      "average": 0
    },
    "DOMqueriesByTagName": {
      "values": [
        3,
        3,
        3,
        3,
        3,
        null
      ],
      "sum": 15,
      "min": 3,
      "max": 3,
      "median": 3,
      "average": 3
    },
    "DOMqueriesByQuerySelectorAll": {
      "values": [
        0,
        0,
        0,
        0,
        0,
        null
      ],
      "sum": 0,
      "min": 0,
      "max": 0,
      "median": 0,
      "average": 0
    },
    "DOMinserts": {
      "values": [
        4,
        4,
        4,
        4,
        4,
        null
      ],
      "sum": 20,
      "min": 4,
      "max": 4,
      "median": 4,
      "average": 4
    },
    "DOMqueriesDuplicated": {
      "values": [
        2,
        2,
        2,
        2,
        2,
        null
      ],
      "sum": 10,
      "min": 2,
      "max": 2,
      "median": 2,
      "average": 2
    },
    "eventsBound": {
      "values": [
        0,
        0,
        0,
        0,
        0,
        null
      ],
      "sum": 0,
      "min": 0,
      "max": 0,
      "median": 0,
      "average": 0
    },
    "globalVariables": {
      "values": [
        55,
        55,
        55,
        55,
        55,
        null
      ],
      "sum": 275,
      "min": 55,
      "max": 55,
      "median": 55,
      "average": 55
    },
    "globalVariablesFalsy": {
      "values": [
        0,
        0,
        0,
        0,
        0,
        null
      ],
      "sum": 0,
      "min": 0,
      "max": 0,
      "median": 0,
      "average": 0
    },
    "headersCount": {
      "values": [
        352,
        352,
        352,
        352,
        352,
        null
      ],
      "sum": 1760,
      "min": 352,
      "max": 352,
      "median": 352,
      "average": 352
    },
    "headersSentCount": {
      "values": [
        83,
        83,
        83,
        83,
        83,
        null
      ],
      "sum": 415,
      "min": 83,
      "max": 83,
      "median": 83,
      "average": 83
    },
    "headersRecvCount": {
      "values": [
        269,
        269,
        269,
        269,
        269,
        null
      ],
      "sum": 1345,
      "min": 269,
      "max": 269,
      "median": 269,
      "average": 269
    },
    "headersSize": {
      "values": [
        11388,
        11389,
        11855,
        11857,
        11857,
        null
      ],
      "sum": 58346,
      "min": 11388,
      "max": 11857,
      "median": 11855,
      "average": 11669.2
    },
    "headersSentSize": {
      "values": [
        2888,
        2888,
        2888,
        2888,
        2888,
        null
      ],
      "sum": 14440,
      "min": 2888,
      "max": 2888,
      "median": 2888,
      "average": 2888
    },
    "headersRecvSize": {
      "values": [
        8500,
        8501,
        8967,
        8969,
        8969,
        null
      ],
      "sum": 43906,
      "min": 8500,
      "max": 8969,
      "median": 8967,
      "average": 8781.2
    },
    "headersBiggerThanContent": {
      "values": [
        2,
        2,
        2,
        2,
        2,
        null
      ],
      "sum": 10,
      "min": 2,
      "max": 2,
      "median": 2,
      "average": 2
    },
    "documentWriteCalls": {
      "values": [
        0,
        0,
        0,
        0,
        0,
        null
      ],
      "sum": 0,
      "min": 0,
      "max": 0,
      "median": 0,
      "average": 0
    },
    "evalCalls": {
      "values": [
        0,
        0,
        0,
        0,
        0,
        null
      ],
      "sum": 0,
      "min": 0,
      "max": 0,
      "median": 0,
      "average": 0
    },
    "jQueryOnDOMReadyFunctions": {
      "values": [
        0,
        0,
        0,
        0,
        0,
        null
      ],
      "sum": 0,
      "min": 0,
      "max": 0,
      "median": 0,
      "average": 0
    },
    "jQuerySizzleCalls": {
      "values": [
        0,
        0,
        0,
        0,
        0,
        null
      ],
      "sum": 0,
      "min": 0,
      "max": 0,
      "median": 0,
      "average": 0
    },
    "jsErrors": {
      "values": [
        0,
        0,
        0,
        0,
        0,
        null
      ],
      "sum": 0,
      "min": 0,
      "max": 0,
      "median": 0,
      "average": 0
    },
    "redirects": {
      "values": [
        0,
        0,
        0,
        0,
        0,
        null
      ],
      "sum": 0,
      "min": 0,
      "max": 0,
      "median": 0,
      "average": 0
    },
    "redirectsTime": {
      "values": [
        0,
        0,
        0,
        0,
        0,
        null
      ],
      "sum": 0,
      "min": 0,
      "max": 0,
      "median": 0,
      "average": 0
    },
    "assetsNotGzipped": {
      "values": [
        5,
        5,
        5,
        5,
        5,
        null
      ],
      "sum": 25,
      "min": 5,
      "max": 5,
      "median": 5,
      "average": 5
    },
    "assetsWithQueryString": {
      "values": [
        3,
        3,
        3,
        3,
        3,
        null
      ],
      "sum": 15,
      "min": 3,
      "max": 3,
      "median": 3,
      "average": 3
    },
    "smallImages": {
      "values": [
        1,
        1,
        1,
        1,
        1,
        null
      ],
      "sum": 5,
      "min": 1,
      "max": 1,
      "median": 1,
      "average": 1
    },
    "multipleRequests": {
      "values": [
        0,
        0,
        0,
        0,
        0,
        null
      ],
      "sum": 0,
      "min": 0,
      "max": 0,
      "median": 0,
      "average": 0
    },
    "timeToFirstCss": {
      "values": [
        558,
        614,
        618,
        643,
        656,
        null
      ],
      "sum": 3089,
      "min": 558,
      "max": 656,
      "median": 618,
      "average": 617.8
    },
    "timeToFirstJs": {
      "values": [
        732,
        795,
        821,
        857,
        903,
        null
      ],
      "sum": 4108,
      "min": 732,
      "max": 903,
      "median": 821,
      "average": 821.6
    },
    "timeToFirstImage": {
      "values": [
        1554,
        1689,
        1707,
        1920,
        2267,
        null
      ],
      "sum": 9137,
      "min": 1554,
      "max": 2267,
      "median": 1707,
      "average": 1827.4
    },
    "onDOMReadyTime": {
      "values": [
        895,
        1072,
        1250,
        1450,
        1566,
        null
      ],
      "sum": 6233,
      "min": 895,
      "max": 1566,
      "median": 1250,
      "average": 1246.6
    },
    "onDOMReadyTimeEnd": {
      "values": [
        896,
        1074,
        1259,
        1452,
        1567,
        null
      ],
      "sum": 6248,
      "min": 896,
      "max": 1567,
      "median": 1259,
      "average": 1249.6
    },
    "windowOnLoadTime": {
      "values": [
        2883,
        3056,
        3076,
        3163,
        3366,
        null
      ],
      "sum": 15544,
      "min": 2883,
      "max": 3366,
      "median": 3076,
      "average": 3108.8
    },
    "windowOnLoadTimeEnd": {
      "values": [
        2885,
        3057,
        3077,
        3164,
        3367,
        null
      ],
      "sum": 15550,
      "min": 2885,
      "max": 3367,
      "median": 3077,
      "average": 3110
    },
    "timeBackend": {
      "values": [
        12,
        12,
        14,
        15,
        15,
        null
      ],
      "sum": 68,
      "min": 12,
      "max": 15,
      "median": 14,
      "average": 13.6
    },
    "timeFrontend": {
      "values": [
        85,
        85,
        86,
        88,
        88,
        null
      ],
      "sum": 432,
      "min": 85,
      "max": 88,
      "median": 86,
      "average": 86.4
    },
    "windowAlerts": {
      "values": [
        0,
        0,
        0,
        0,
        0,
        null
      ],
      "sum": 0,
      "min": 0,
      "max": 0,
      "median": 0,
      "average": 0
    },
    "windowConfirms": {
      "values": [
        0,
        0,
        0,
        0,
        0,
        null
      ],
      "sum": 0,
      "min": 0,
      "max": 0,
      "median": 0,
      "average": 0
    },
    "windowPrompts": {
      "values": [
        0,
        0,
        0,
        0,
        0,
        null
      ],
      "sum": 0,
      "min": 0,
      "max": 0,
      "median": 0,
      "average": 0
    },
    "cookiesSent": {
      "values": [
        0,
        0,
        0,
        0,
        0,
        null
      ],
      "sum": 0,
      "min": 0,
      "max": 0,
      "median": 0,
      "average": 0
    },
    "cookiesRecv": {
      "values": [
        174,
        174,
        640,
        643,
        643,
        null
      ],
      "sum": 2274,
      "min": 174,
      "max": 643,
      "median": 640,
      "average": 454.8
    },
    "domainsWithCookies": {
      "values": [
        1,
        1,
        1,
        1,
        1,
        null
      ],
      "sum": 5,
      "min": 1,
      "max": 1,
      "median": 1,
      "average": 1
    },
    "documentCookiesLength": {
      "values": [
        192,
        192,
        192,
        193,
        193,
        null
      ],
      "sum": 962,
      "min": 192,
      "max": 193,
      "median": 192,
      "average": 192.4
    },
    "documentCookiesCount": {
      "values": [
        4,
        4,
        4,
        4,
        4,
        null
      ],
      "sum": 20,
      "min": 4,
      "max": 4,
      "median": 4,
      "average": 4
    },
    "bodyHTMLSize": {
      "values": [
        10791,
        10792,
        10792,
        10892,
        11027,
        null
      ],
      "sum": 54294,
      "min": 10791,
      "max": 11027,
      "median": 10792,
      "average": 10858.8
    },
    "iframesCount": {
      "values": [
        0,
        0,
        0,
        0,
        0,
        null
      ],
      "sum": 0,
      "min": 0,
      "max": 0,
      "median": 0,
      "average": 0
    },
    "imagesWithoutDimensions": {
      "values": [
        16,
        16,
        16,
        16,
        16,
        null
      ],
      "sum": 80,
      "min": 16,
      "max": 16,
      "median": 16,
      "average": 16
    },
    "commentsSize": {
      "values": [
        53,
        53,
        53,
        53,
        53,
        null
      ],
      "sum": 265,
      "min": 53,
      "max": 53,
      "median": 53,
      "average": 53
    },
    "hiddenContentSize": {
      "values": [
        61,
        61,
        61,
        61,
        61,
        null
      ],
      "sum": 305,
      "min": 61,
      "max": 61,
      "median": 61,
      "average": 61
    },
    "whiteSpacesSize": {
      "values": [
        4,
        4,
        4,
        4,
        4,
        null
      ],
      "sum": 20,
      "min": 4,
      "max": 4,
      "median": 4,
      "average": 4
    },
    "DOMelementsCount": {
      "values": [
        198,
        198,
        198,
        198,
        199,
        null
      ],
      "sum": 991,
      "min": 198,
      "max": 199,
      "median": 198,
      "average": 198.2
    },
    "DOMelementMaxDepth": {
      "values": [
        10,
        10,
        10,
        10,
        10,
        null
      ],
      "sum": 50,
      "min": 10,
      "max": 10,
      "median": 10,
      "average": 10
    },
    "nodesWithInlineCSS": {
      "values": [
        0,
        0,
        0,
        0,
        0,
        null
      ],
      "sum": 0,
      "min": 0,
      "max": 0,
      "median": 0,
      "average": 0
    },
    "localStorageEntries": {
      "values": [
        0,
        0,
        0,
        0,
        0,
        null
      ],
      "sum": 0,
      "min": 0,
      "max": 0,
      "median": 0,
      "average": 0
    },
    "smallestResponse": {
      "values": [
        35,
        35,
        35,
        35,
        35,
        null
      ],
      "sum": 175,
      "min": 35,
      "max": 35,
      "median": 35,
      "average": 35
    },
    "biggestResponse": {
      "values": [
        95122,
        95122,
        95122,
        95122,
        95122,
        null
      ],
      "sum": 475610,
      "min": 95122,
      "max": 95122,
      "median": 95122,
      "average": 95122
    },
    "fastestResponse": {
      "values": [
        38,
        41,
        58,
        97,
        102,
        null
      ],
      "sum": 336,
      "min": 38,
      "max": 102,
      "median": 58,
      "average": 67.2
    },
    "slowestResponse": {
      "values": [
        1669,
        2066,
        2131,
        2205,
        2331,
        null
      ],
      "sum": 10402,
      "min": 1669,
      "max": 2331,
      "median": 2131,
      "average": 2080.4
    },
    "smallestLatency": {
      "values": [
        38,
        40,
        58,
        97,
        102,
        null
      ],
      "sum": 335,
      "min": 38,
      "max": 102,
      "median": 58,
      "average": 67
    },
    "biggestLatency": {
      "values": [
        1181,
        1250,
        1520,
        1590,
        1680,
        null
      ],
      "sum": 7221,
      "min": 1181,
      "max": 1680,
      "median": 1520,
      "average": 1444.2
    },
    "medianResponse": {
      "values": [
        573,
        584.5,
        602,
        619,
        758,
        null
      ],
      "sum": 3136.5,
      "min": 573,
      "max": 758,
      "median": 602,
      "average": 627.3
    },
    "medianLatency": {
      "values": [
        473,
        475.5,
        492,
        493.5,
        621.5,
        null
      ],
      "sum": 2555.5,
      "min": 473,
      "max": 621.5,
      "median": 492,
      "average": 511.1
    }
  },
  "offenders": {
    "htmlCount": [
      "http://gruntjs.com/ (9.82 kB)"
    ],
    "assetsNotGzipped": [
      "http://gruntjs.com/ (HTML)",
      "http://fonts.googleapis.com/css?family=Lato:400,700 (CSS)",
      "http://gruntjs.com/js/vendor/lib/modernizr.min.js (JS)",
      "http://gruntjs.com/css/main.css (CSS)",
      "http://www.google-analytics.com/ga.js (JS)"
    ],
    "cssCount": [
      "http://fonts.googleapis.com/css?family=Lato:400,700 (0.47 kB)",
      "http://gruntjs.com/css/main.css (92.89 kB)"
    ],
    "oldCachingHeaders": [
      "http://fonts.googleapis.com/css?family=Lato:400,700 - Expires: Wed, 23 Apr 2014 19:57:49 GMT",
      "http://www.google-analytics.com/ga.js - Expires: Thu, 24 Apr 2014 03:17:09 GMT",
      "http://www.google-analytics.com/__utm.gif?utmwv=5.5.0&utms=1&utmn=365335679&utmhn=gruntjs.com&utmcs=UTF-8&utmsr=1920x1080&utmvp=2560x2048&utmsc=32-bit&utmul=de-de&utmje=0&utmfl=-&utmdt=Grunt%3A%20The%20JavaScript%20Task%20Runner&utmhid=1949298360&utmr=-&utmp=%2F&utmht=1398283071719&utmac=UA-34623937-1&utmcc=__utma%3D221136078.870192107.1398283072.1398283072.1398283072.1%3B%2B__utmz%3D221136078.1398283072.1.1.utmcsr%3D(direct)%7Cutmccn%3D(direct)%7Cutmcmd%3D(none)%3B&utmu=q~ - Pragma: no-cache",
      "http://www.google-analytics.com/__utm.gif?utmwv=5.5.0&utms=1&utmn=365335679&utmhn=gruntjs.com&utmcs=UTF-8&utmsr=1920x1080&utmvp=2560x2048&utmsc=32-bit&utmul=de-de&utmje=0&utmfl=-&utmdt=Grunt%3A%20The%20JavaScript%20Task%20Runner&utmhid=1949298360&utmr=-&utmp=%2F&utmht=1398283071719&utmac=UA-34623937-1&utmcc=__utma%3D221136078.870192107.1398283072.1398283072.1398283072.1%3B%2B__utmz%3D221136078.1398283072.1.1.utmcsr%3D(direct)%7Cutmccn%3D(direct)%7Cutmcmd%3D(none)%3B&utmu=q~ - Expires: Wed, 19 Apr 2000 11:43:00 GMT",
      "http://static.adzerk.net/Advertisers/ea529209f3cf4623b79a2ad0d3a04a7c.png - Expires: Tue, 23 Apr 2024 19:03:59 GMT",
      "http://www.google-analytics.com/__utm.gif?utmwv=5.5.0&utms=1&utmn=1084152484&utmhn=gruntjs.com&utmcs=UTF-8&utmsr=1920x1080&utmvp=1280x1024&utmsc=32-bit&utmul=de-de&utmje=0&utmfl=-&utmdt=Grunt%3A%20The%20JavaScript%20Task%20Runner&utmhid=1565166529&utmr=-&utmp=%2F&utmht=1398283071785&utmac=UA-34623937-1&utmcc=__utma%3D221136078.349624065.1398283072.1398283072.1398283072.1%3B%2B__utmz%3D221136078.1398283072.1.1.utmcsr%3D(direct)%7Cutmccn%3D(direct)%7Cutmcmd%3D(none)%3B&utmu=q~ - Pragma: no-cache",
      "http://www.google-analytics.com/__utm.gif?utmwv=5.5.0&utms=1&utmn=1084152484&utmhn=gruntjs.com&utmcs=UTF-8&utmsr=1920x1080&utmvp=1280x1024&utmsc=32-bit&utmul=de-de&utmje=0&utmfl=-&utmdt=Grunt%3A%20The%20JavaScript%20Task%20Runner&utmhid=1565166529&utmr=-&utmp=%2F&utmht=1398283071785&utmac=UA-34623937-1&utmcc=__utma%3D221136078.349624065.1398283072.1398283072.1398283072.1%3B%2B__utmz%3D221136078.1398283072.1.1.utmcsr%3D(direct)%7Cutmccn%3D(direct)%7Cutmcmd%3D(none)%3B&utmu=q~ - Expires: Wed, 19 Apr 2000 11:43:00 GMT",
      "http://static.adzerk.net/Advertisers/a315a7f3eb014d5f917e6aa646abf030.jpg - Expires: Thu, 08 Jun 2023 01:40:25 GMT",
      "http://www.google-analytics.com/__utm.gif?utmwv=5.5.0&utms=1&utmn=1305650803&utmhn=gruntjs.com&utmcs=UTF-8&utmsr=1920x1080&utmvp=1280x1024&utmsc=32-bit&utmul=de-de&utmje=0&utmfl=-&utmdt=Grunt%3A%20The%20JavaScript%20Task%20Runner&utmhid=1378832192&utmr=-&utmp=%2F&utmht=1398283070707&utmac=UA-34623937-1&utmcc=__utma%3D221136078.1153693557.1398283071.1398283071.1398283071.1%3B%2B__utmz%3D221136078.1398283071.1.1.utmcsr%3D(direct)%7Cutmccn%3D(direct)%7Cutmcmd%3D(none)%3B&utmu=q~ - Pragma: no-cache",
      "http://www.google-analytics.com/__utm.gif?utmwv=5.5.0&utms=1&utmn=1305650803&utmhn=gruntjs.com&utmcs=UTF-8&utmsr=1920x1080&utmvp=1280x1024&utmsc=32-bit&utmul=de-de&utmje=0&utmfl=-&utmdt=Grunt%3A%20The%20JavaScript%20Task%20Runner&utmhid=1378832192&utmr=-&utmp=%2F&utmht=1398283070707&utmac=UA-34623937-1&utmcc=__utma%3D221136078.1153693557.1398283071.1398283071.1398283071.1%3B%2B__utmz%3D221136078.1398283071.1.1.utmcsr%3D(direct)%7Cutmccn%3D(direct)%7Cutmcmd%3D(none)%3B&utmu=q~ - Expires: Wed, 19 Apr 2000 11:43:00 GMT",
      "http://static.adzerk.net/Advertisers/020dc19f551e443585f221f54eb94c4b.png - Expires: Wed, 17 Apr 2024 04:05:12 GMT",
      "http://www.google-analytics.com/__utm.gif?utmwv=5.5.0&utms=1&utmn=486959357&utmhn=gruntjs.com&utmcs=UTF-8&utmsr=1920x1080&utmvp=1280x1024&utmsc=32-bit&utmul=de-de&utmje=0&utmfl=-&utmdt=Grunt%3A%20The%20JavaScript%20Task%20Runner&utmhid=1175971230&utmr=-&utmp=%2F&utmht=1398283072222&utmac=UA-34623937-1&utmcc=__utma%3D221136078.648545905.1398283072.1398283072.1398283072.1%3B%2B__utmz%3D221136078.1398283072.1.1.utmcsr%3D(direct)%7Cutmccn%3D(direct)%7Cutmcmd%3D(none)%3B&utmu=q~ - Pragma: no-cache",
      "http://www.google-analytics.com/__utm.gif?utmwv=5.5.0&utms=1&utmn=486959357&utmhn=gruntjs.com&utmcs=UTF-8&utmsr=1920x1080&utmvp=1280x1024&utmsc=32-bit&utmul=de-de&utmje=0&utmfl=-&utmdt=Grunt%3A%20The%20JavaScript%20Task%20Runner&utmhid=1175971230&utmr=-&utmp=%2F&utmht=1398283072222&utmac=UA-34623937-1&utmcc=__utma%3D221136078.648545905.1398283072.1398283072.1398283072.1%3B%2B__utmz%3D221136078.1398283072.1.1.utmcsr%3D(direct)%7Cutmccn%3D(direct)%7Cutmcmd%3D(none)%3B&utmu=q~ - Expires: Wed, 19 Apr 2000 11:43:00 GMT",
      "http://www.google-analytics.com/__utm.gif?utmwv=5.5.0&utms=1&utmn=521956102&utmhn=gruntjs.com&utmcs=UTF-8&utmsr=1920x1080&utmvp=1280x1024&utmsc=32-bit&utmul=de-de&utmje=0&utmfl=-&utmdt=Grunt%3A%20The%20JavaScript%20Task%20Runner&utmhid=1117730328&utmr=-&utmp=%2F&utmht=1398283070900&utmac=UA-34623937-1&utmcc=__utma%3D221136078.1295273603.1398283071.1398283071.1398283071.1%3B%2B__utmz%3D221136078.1398283071.1.1.utmcsr%3D(direct)%7Cutmccn%3D(direct)%7Cutmcmd%3D(none)%3B&utmu=q~ - Pragma: no-cache",
      "http://www.google-analytics.com/__utm.gif?utmwv=5.5.0&utms=1&utmn=521956102&utmhn=gruntjs.com&utmcs=UTF-8&utmsr=1920x1080&utmvp=1280x1024&utmsc=32-bit&utmul=de-de&utmje=0&utmfl=-&utmdt=Grunt%3A%20The%20JavaScript%20Task%20Runner&utmhid=1117730328&utmr=-&utmp=%2F&utmht=1398283070900&utmac=UA-34623937-1&utmcc=__utma%3D221136078.1295273603.1398283071.1398283071.1398283071.1%3B%2B__utmz%3D221136078.1398283071.1.1.utmcsr%3D(direct)%7Cutmccn%3D(direct)%7Cutmcmd%3D(none)%3B&utmu=q~ - Expires: Wed, 19 Apr 2000 11:43:00 GMT",
      "http://static.adzerk.net/Advertisers/327c84a8e1a64e36b74beeba7ec8a08b.jpg - Expires: Mon, 15 May 2023 13:07:56 GMT"
    ],
    "cachingTooShort": [
      "http://fonts.googleapis.com/css?family=Lato:400,700 cached for 86400 s",
      "http://www.google-analytics.com/ga.js cached for 43200 s"
    ],
    "assetsWithQueryString": [
      "http://fonts.googleapis.com/css?family=Lato:400,700 (CSS)",
      "http://engine.adzerk.net/ados?t=1398283072066&request=%7B%22Placements%22:%5B%7B%22A%22:4433,%22S%22:27854,%22D%22:%22azk48893%22,%22AT%22:1%7D%5D,%22Keywords%22:%22undefined%22,%22Referrer%22:%22%22,%22IsAsync%22:true%7D (JS)",
      "http://engine.adzerk.net/i.gif?e=eyJhdiI6MjAwNjksImF0IjoxLCJjbSI6MjgxMDEsImNoIjo2OTkyLCJjciI6MTQ5NTE5LCJkaSI6IjE2NWIzZWYzMWRkNjRmMDA5ZTkzMjhkZGFmYjlhMzJlIiwiZG0iOjEsImZjIjoyMDMxMDcsImZsIjo0Njk3Nywia3ciOiJ1bmRlZmluZWQiLCJudyI6NDQzMywicGMiOjAsInByIjoxNjI5MSwicnQiOjEsInN0IjoyNzg1NCwidHIiOnRydWUsInVrIjoidWUxLWJmN2UyNmFiM2E3NTQxZmU4ZDhlNjk3YzY4ZTUyNzAzIiwidHMiOjEzOTgyODMwOTQ5ODF9&s=0bGqzQjiXoYnoQDjbof1KZMtS_g (IMAGE)",
      "http://engine.adzerk.net/ados?t=1398283072019&request=%7B%22Placements%22:%5B%7B%22A%22:4433,%22S%22:27854,%22D%22:%22azk48893%22,%22AT%22:1%7D%5D,%22Keywords%22:%22undefined%22,%22Referrer%22:%22%22,%22IsAsync%22:true%7D (JS)",
      "http://engine.adzerk.net/i.gif?e=eyJhdiI6MjA3ODIsImF0IjoxLCJjbSI6MjkxNDIsImNoIjo2OTkyLCJjciI6NzAwMjQsImRpIjoiNzc1MmNjODc3OTk1NDNiMzg4NGJlNmI0YWFhNDcyMzYiLCJkbSI6MSwiZmMiOjk4MTk0LCJmbCI6NDg3OTEsImt3IjoidW5kZWZpbmVkIiwibnciOjQ0MzMsInBjIjowLCJwciI6MTYyOTEsInJ0IjoxLCJzdCI6Mjc4NTQsInVrIjoidWUxLTM2YjlmMzU4YzE1YTQ0YTI5Mjg4Zjc5NWY0Mzg0YjhhIiwidHMiOjEzOTgyODMxMTkxODZ9&s=u_-6631ZUDgB5aef2BawmZr15w0 (IMAGE)",
      "http://engine.adzerk.net/ados?t=1398283070583&request=%7B%22Placements%22:%5B%7B%22A%22:4433,%22S%22:27854,%22D%22:%22azk48893%22,%22AT%22:1%7D%5D,%22Keywords%22:%22undefined%22,%22Referrer%22:%22%22,%22IsAsync%22:true%7D (JS)",
      "http://engine.adzerk.net/i.gif?e=eyJhdiI6MjAwNjksImF0IjoxLCJjbSI6MjgxMDEsImNoIjo2OTkyLCJjciI6Mjc2NjA3LCJkaSI6ImQzZGIxYjZhNTIzYzQzZjE4MmZhYjkxMzAwYmIwMDM5IiwiZG0iOjEsImZjIjozNDE5OTYsImZsIjo0Njk3Nywia3ciOiJ1bmRlZmluZWQiLCJudyI6NDQzMywicGMiOjAsInByIjoxNjI5MSwicnQiOjEsInN0IjoyNzg1NCwidHIiOnRydWUsInVrIjoidWUxLTExYjUwZmU4ZjY5NDQxYjlhNzU2NTJhYzY4ZWM0ZDk1IiwidHMiOjEzOTgyODMxMDUwMzF9&s=HqmSw42vH7iiBNY9jVYMMY-CdVI (IMAGE)",
      "http://engine.adzerk.net/ados?t=1398283072092&request=%7B%22Placements%22:%5B%7B%22A%22:4433,%22S%22:27854,%22D%22:%22azk48893%22,%22AT%22:1%7D%5D,%22Keywords%22:%22undefined%22,%22Referrer%22:%22%22,%22IsAsync%22:true%7D (JS)",
      "http://engine.adzerk.net/i.gif?e=eyJhdiI6MjA3ODIsImF0IjoxLCJjbSI6MjkxNDIsImNoIjo2OTkyLCJjciI6NzAwMjQsImRpIjoiYTQzMDRhZDY4ODQyNDAyYmIzMDA3YTU4ODZlYTRlOWMiLCJkbSI6MSwiZmMiOjk4MTk0LCJmbCI6NDg3OTEsImt3IjoidW5kZWZpbmVkIiwibnciOjQ0MzMsInBjIjowLCJwciI6MTYyOTEsInJ0IjoxLCJzdCI6Mjc4NTQsInVrIjoidWUxLTBkZDI1OTUwODE5YjQzMjA5YzEzNjk2YzQ0YjU1NDY4IiwidHMiOjEzOTgyODMwNzUwNDR9&s=5o_X5iGloDwHyZZwKCR0s2s5vkY (IMAGE)",
      "http://engine.adzerk.net/ados?t=1398283070593&request=%7B%22Placements%22:%5B%7B%22A%22:4433,%22S%22:27854,%22D%22:%22azk48893%22,%22AT%22:1%7D%5D,%22Keywords%22:%22undefined%22,%22Referrer%22:%22%22,%22IsAsync%22:true%7D (JS)",
      "http://engine.adzerk.net/i.gif?e=eyJhdiI6MjAwNjksImF0IjoxLCJjbSI6MjgxMDEsImNoIjo2OTkyLCJjciI6Njk4MDgsImRpIjoiZWUzNzc1NmQyNGQxNGRlY2FmMjJjOGRjYTQ5ZWFmZTQiLCJkbSI6MSwiZmMiOjk3Nzk3LCJmbCI6NDY5NzcsImt3IjoidW5kZWZpbmVkIiwibnciOjQ0MzMsInBjIjowLCJwciI6MTYyOTEsInJ0IjoxLCJzdCI6Mjc4NTQsInRyIjp0cnVlLCJ1ayI6InVlMS02NWEyYjNkZjM4MDQ0NWI1ODI4NzljNDdiNzhjNzVhZSIsInRzIjoxMzk4MjgzMTExMzUxfQ&s=h41rTyWaa6AKXjumf6GuC0DvlUk (IMAGE)"
    ],
    "timeToFirstCss": [
      "http://fonts.googleapis.com/css?family=Lato:400,700 received in 558 ms",
      "http://fonts.googleapis.com/css?family=Lato:400,700 received in 643 ms",
      "http://fonts.googleapis.com/css?family=Lato:400,700 received in 614 ms",
      "http://fonts.googleapis.com/css?family=Lato:400,700 received in 618 ms",
      "http://fonts.googleapis.com/css?family=Lato:400,700 received in 656 ms"
    ],
    "jsCount": [
      "http://gruntjs.com/js/vendor/lib/modernizr.min.js (3.69 kB)",
      "http://www.google-analytics.com/ga.js (13.50 kB)",
      "http://static.adzerk.net/ados.js (21.09 kB)",
      "http://engine.adzerk.net/ados?t=1398283072066&request=%7B%22Placements%22:%5B%7B%22A%22:4433,%22S%22:27854,%22D%22:%22azk48893%22,%22AT%22:1%7D%5D,%22Keywords%22:%22undefined%22,%22Referrer%22:%22%22,%22IsAsync%22:true%7D (2.07 kB)",
      "http://www.google-analytics.com/ga.js (1.04 kB)",
      "http://engine.adzerk.net/ados?t=1398283072019&request=%7B%22Placements%22:%5B%7B%22A%22:4433,%22S%22:27854,%22D%22:%22azk48893%22,%22AT%22:1%7D%5D,%22Keywords%22:%22undefined%22,%22Referrer%22:%22%22,%22IsAsync%22:true%7D (2.04 kB)",
      "http://engine.adzerk.net/ados?t=1398283070583&request=%7B%22Placements%22:%5B%7B%22A%22:4433,%22S%22:27854,%22D%22:%22azk48893%22,%22AT%22:1%7D%5D,%22Keywords%22:%22undefined%22,%22Referrer%22:%22%22,%22IsAsync%22:true%7D (2.48 kB)",
      "http://www.google-analytics.com/ga.js (2.42 kB)",
      "http://engine.adzerk.net/ados?t=1398283072092&request=%7B%22Placements%22:%5B%7B%22A%22:4433,%22S%22:27854,%22D%22:%22azk48893%22,%22AT%22:1%7D%5D,%22Keywords%22:%22undefined%22,%22Referrer%22:%22%22,%22IsAsync%22:true%7D (2.04 kB)",
      "http://engine.adzerk.net/ados?t=1398283070593&request=%7B%22Placements%22:%5B%7B%22A%22:4433,%22S%22:27854,%22D%22:%22azk48893%22,%22AT%22:1%7D%5D,%22Keywords%22:%22undefined%22,%22Referrer%22:%22%22,%22IsAsync%22:true%7D (2.17 kB)"
    ],
    "cachingDisabled": [
      "http://gruntjs.com/js/vendor/lib/modernizr.min.js",
      "http://gruntjs.com/css/main.css",
      "http://gruntjs.com/img/logo-handlebars.jpg",
      "http://gruntjs.com/img/logo-coffeescript.jpg",
      "http://gruntjs.com/img/logo-jade.jpg",
      "http://gruntjs.com/img/logo-jshint.jpg",
      "http://gruntjs.com/img/logo-less.jpg",
      "http://gruntjs.com/img/logo-requirejs.jpg",
      "http://gruntjs.com/img/logo-sass.jpg",
      "http://gruntjs.com/img/logo-sylus.jpg",
      "http://gruntjs.com/img/logo-twitter.jpg",
      "http://gruntjs.com/img/logo-jquery.jpg",
      "http://gruntjs.com/img/logo-adobe.jpg",
      "http://gruntjs.com/img/logo-modernizr.jpg",
      "http://gruntjs.com/img/logo-bitovi.jpg",
      "http://gruntjs.com/img/grunt-logo.svg",
      "http://gruntjs.com/img/logo-bocoup.jpg",
      "http://gruntjs.com/img/logo-saucelabs.jpg",
      "http://gruntjs.com/img/logo-fg.jpg",
      "http://gruntjs.com/fonts/icomoon.svg"
    ],
    "timeToFirstJs": [
      "http://gruntjs.com/js/vendor/lib/modernizr.min.js received in 795 ms",
      "http://gruntjs.com/js/vendor/lib/modernizr.min.js received in 732 ms",
      "http://gruntjs.com/js/vendor/lib/modernizr.min.js received in 857 ms",
      "http://gruntjs.com/js/vendor/lib/modernizr.min.js received in 821 ms",
      "http://gruntjs.com/js/vendor/lib/modernizr.min.js received in 903 ms"
    ],
    "imageCount": [
      "http://gruntjs.com/img/logo-handlebars.jpg (8.43 kB)",
      "http://gruntjs.com/img/logo-coffeescript.jpg (3.59 kB)",
      "http://gruntjs.com/img/logo-jade.jpg (5.56 kB)",
      "http://gruntjs.com/img/logo-jshint.jpg (4.52 kB)",
      "http://gruntjs.com/img/logo-less.jpg (5.66 kB)",
      "http://gruntjs.com/img/logo-requirejs.jpg (5.24 kB)",
      "http://gruntjs.com/img/logo-sass.jpg (5.78 kB)",
      "http://gruntjs.com/img/logo-sylus.jpg (5.21 kB)",
      "http://gruntjs.com/img/logo-twitter.jpg (3.60 kB)",
      "http://gruntjs.com/img/logo-jquery.jpg (4.52 kB)",
      "http://gruntjs.com/img/logo-adobe.jpg (4.61 kB)",
      "http://gruntjs.com/img/logo-modernizr.jpg (6.73 kB)",
      "http://gruntjs.com/img/logo-bitovi.jpg (5.03 kB)",
      "http://www.google-analytics.com/__utm.gif?utmwv=5.5.0&utms=1&utmn=365335679&utmhn=gruntjs.com&utmcs=UTF-8&utmsr=1920x1080&utmvp=2560x2048&utmsc=32-bit&utmul=de-de&utmje=0&utmfl=-&utmdt=Grunt%3A%20The%20JavaScript%20Task%20Runner&utmhid=1949298360&utmr=-&utmp=%2F&utmht=1398283071719&utmac=UA-34623937-1&utmcc=__utma%3D221136078.870192107.1398283072.1398283072.1398283072.1%3B%2B__utmz%3D221136078.1398283072.1.1.utmcsr%3D(direct)%7Cutmccn%3D(direct)%7Cutmcmd%3D(none)%3B&utmu=q~ (0.03 kB)",
      "http://gruntjs.com/img/grunt-logo.svg (28.96 kB)",
      "http://gruntjs.com/img/logo-bocoup.jpg (10.08 kB)",
      "http://gruntjs.com/img/logo-saucelabs.jpg (8.23 kB)",
      "http://gruntjs.com/img/logo-fg.jpg (5.88 kB)",
      "http://gruntjs.com/fonts/icomoon.svg (10.14 kB)",
      "http://static.adzerk.net/Advertisers/ea529209f3cf4623b79a2ad0d3a04a7c.png (6.00 kB)",
      "http://engine.adzerk.net/i.gif?e=eyJhdiI6MjAwNjksImF0IjoxLCJjbSI6MjgxMDEsImNoIjo2OTkyLCJjciI6MTQ5NTE5LCJkaSI6IjE2NWIzZWYzMWRkNjRmMDA5ZTkzMjhkZGFmYjlhMzJlIiwiZG0iOjEsImZjIjoyMDMxMDcsImZsIjo0Njk3Nywia3ciOiJ1bmRlZmluZWQiLCJudyI6NDQzMywicGMiOjAsInByIjoxNjI5MSwicnQiOjEsInN0IjoyNzg1NCwidHIiOnRydWUsInVrIjoidWUxLWJmN2UyNmFiM2E3NTQxZmU4ZDhlNjk3YzY4ZTUyNzAzIiwidHMiOjEzOTgyODMwOTQ5ODF9&s=0bGqzQjiXoYnoQDjbof1KZMtS_g (0.04 kB)",
      "http://www.google-analytics.com/__utm.gif?utmwv=5.5.0&utms=1&utmn=1084152484&utmhn=gruntjs.com&utmcs=UTF-8&utmsr=1920x1080&utmvp=1280x1024&utmsc=32-bit&utmul=de-de&utmje=0&utmfl=-&utmdt=Grunt%3A%20The%20JavaScript%20Task%20Runner&utmhid=1565166529&utmr=-&utmp=%2F&utmht=1398283071785&utmac=UA-34623937-1&utmcc=__utma%3D221136078.349624065.1398283072.1398283072.1398283072.1%3B%2B__utmz%3D221136078.1398283072.1.1.utmcsr%3D(direct)%7Cutmccn%3D(direct)%7Cutmcmd%3D(none)%3B&utmu=q~ (0.03 kB)",
      "http://engine.adzerk.net/i.gif?e=eyJhdiI6MjA3ODIsImF0IjoxLCJjbSI6MjkxNDIsImNoIjo2OTkyLCJjciI6NzAwMjQsImRpIjoiNzc1MmNjODc3OTk1NDNiMzg4NGJlNmI0YWFhNDcyMzYiLCJkbSI6MSwiZmMiOjk4MTk0LCJmbCI6NDg3OTEsImt3IjoidW5kZWZpbmVkIiwibnciOjQ0MzMsInBjIjowLCJwciI6MTYyOTEsInJ0IjoxLCJzdCI6Mjc4NTQsInVrIjoidWUxLTM2YjlmMzU4YzE1YTQ0YTI5Mjg4Zjc5NWY0Mzg0YjhhIiwidHMiOjEzOTgyODMxMTkxODZ9&s=u_-6631ZUDgB5aef2BawmZr15w0 (0.04 kB)",
      "http://static.adzerk.net/Advertisers/a315a7f3eb014d5f917e6aa646abf030.jpg (29.54 kB)",
      "http://www.google-analytics.com/__utm.gif?utmwv=5.5.0&utms=1&utmn=1305650803&utmhn=gruntjs.com&utmcs=UTF-8&utmsr=1920x1080&utmvp=1280x1024&utmsc=32-bit&utmul=de-de&utmje=0&utmfl=-&utmdt=Grunt%3A%20The%20JavaScript%20Task%20Runner&utmhid=1378832192&utmr=-&utmp=%2F&utmht=1398283070707&utmac=UA-34623937-1&utmcc=__utma%3D221136078.1153693557.1398283071.1398283071.1398283071.1%3B%2B__utmz%3D221136078.1398283071.1.1.utmcsr%3D(direct)%7Cutmccn%3D(direct)%7Cutmcmd%3D(none)%3B&utmu=q~ (0.03 kB)",
      "http://engine.adzerk.net/i.gif?e=eyJhdiI6MjAwNjksImF0IjoxLCJjbSI6MjgxMDEsImNoIjo2OTkyLCJjciI6Mjc2NjA3LCJkaSI6ImQzZGIxYjZhNTIzYzQzZjE4MmZhYjkxMzAwYmIwMDM5IiwiZG0iOjEsImZjIjozNDE5OTYsImZsIjo0Njk3Nywia3ciOiJ1bmRlZmluZWQiLCJudyI6NDQzMywicGMiOjAsInByIjoxNjI5MSwicnQiOjEsInN0IjoyNzg1NCwidHIiOnRydWUsInVrIjoidWUxLTExYjUwZmU4ZjY5NDQxYjlhNzU2NTJhYzY4ZWM0ZDk1IiwidHMiOjEzOTgyODMxMDUwMzF9&s=HqmSw42vH7iiBNY9jVYMMY-CdVI (0.04 kB)",
      "http://static.adzerk.net/Advertisers/020dc19f551e443585f221f54eb94c4b.png (4.48 kB)",
      "http://www.google-analytics.com/__utm.gif?utmwv=5.5.0&utms=1&utmn=486959357&utmhn=gruntjs.com&utmcs=UTF-8&utmsr=1920x1080&utmvp=1280x1024&utmsc=32-bit&utmul=de-de&utmje=0&utmfl=-&utmdt=Grunt%3A%20The%20JavaScript%20Task%20Runner&utmhid=1175971230&utmr=-&utmp=%2F&utmht=1398283072222&utmac=UA-34623937-1&utmcc=__utma%3D221136078.648545905.1398283072.1398283072.1398283072.1%3B%2B__utmz%3D221136078.1398283072.1.1.utmcsr%3D(direct)%7Cutmccn%3D(direct)%7Cutmcmd%3D(none)%3B&utmu=q~ (0.03 kB)",
      "http://engine.adzerk.net/i.gif?e=eyJhdiI6MjA3ODIsImF0IjoxLCJjbSI6MjkxNDIsImNoIjo2OTkyLCJjciI6NzAwMjQsImRpIjoiYTQzMDRhZDY4ODQyNDAyYmIzMDA3YTU4ODZlYTRlOWMiLCJkbSI6MSwiZmMiOjk4MTk0LCJmbCI6NDg3OTEsImt3IjoidW5kZWZpbmVkIiwibnciOjQ0MzMsInBjIjowLCJwciI6MTYyOTEsInJ0IjoxLCJzdCI6Mjc4NTQsInVrIjoidWUxLTBkZDI1OTUwODE5YjQzMjA5YzEzNjk2YzQ0YjU1NDY4IiwidHMiOjEzOTgyODMwNzUwNDR9&s=5o_X5iGloDwHyZZwKCR0s2s5vkY (0.04 kB)",
      "http://www.google-analytics.com/__utm.gif?utmwv=5.5.0&utms=1&utmn=521956102&utmhn=gruntjs.com&utmcs=UTF-8&utmsr=1920x1080&utmvp=1280x1024&utmsc=32-bit&utmul=de-de&utmje=0&utmfl=-&utmdt=Grunt%3A%20The%20JavaScript%20Task%20Runner&utmhid=1117730328&utmr=-&utmp=%2F&utmht=1398283070900&utmac=UA-34623937-1&utmcc=__utma%3D221136078.1295273603.1398283071.1398283071.1398283071.1%3B%2B__utmz%3D221136078.1398283071.1.1.utmcsr%3D(direct)%7Cutmccn%3D(direct)%7Cutmcmd%3D(none)%3B&utmu=q~ (0.03 kB)",
      "http://engine.adzerk.net/i.gif?e=eyJhdiI6MjAwNjksImF0IjoxLCJjbSI6MjgxMDEsImNoIjo2OTkyLCJjciI6Njk4MDgsImRpIjoiZWUzNzc1NmQyNGQxNGRlY2FmMjJjOGRjYTQ5ZWFmZTQiLCJkbSI6MSwiZmMiOjk3Nzk3LCJmbCI6NDY5NzcsImt3IjoidW5kZWZpbmVkIiwibnciOjQ0MzMsInBjIjowLCJwciI6MTYyOTEsInJ0IjoxLCJzdCI6Mjc4NTQsInRyIjp0cnVlLCJ1ayI6InVlMS02NWEyYjNkZjM4MDQ0NWI1ODI4NzljNDdiNzhjNzVhZSIsInRzIjoxMzk4MjgzMTExMzUxfQ&s=h41rTyWaa6AKXjumf6GuC0DvlUk (0.04 kB)",
      "http://static.adzerk.net/Advertisers/327c84a8e1a64e36b74beeba7ec8a08b.jpg (28.22 kB)"
    ],
    "timeToFirstImage": [
      "http://gruntjs.com/img/logo-handlebars.jpg received in 1707 ms",
      "http://gruntjs.com/img/logo-coffeescript.jpg received in 2267 ms",
      "http://gruntjs.com/img/logo-handlebars.jpg received in 1554 ms",
      "http://gruntjs.com/img/logo-coffeescript.jpg received in 1920 ms",
      "http://gruntjs.com/img/logo-coffeescript.jpg received in 1689 ms"
    ],
    "cacheHits": [
      "http://www.google-analytics.com/ga.js",
      "http://www.google-analytics.com/__utm.gif?utmwv=5.5.0&utms=1&utmn=365335679&utmhn=gruntjs.com&utmcs=UTF-8&utmsr=1920x1080&utmvp=2560x2048&utmsc=32-bit&utmul=de-de&utmje=0&utmfl=-&utmdt=Grunt%3A%20The%20JavaScript%20Task%20Runner&utmhid=1949298360&utmr=-&utmp=%2F&utmht=1398283071719&utmac=UA-34623937-1&utmcc=__utma%3D221136078.870192107.1398283072.1398283072.1398283072.1%3B%2B__utmz%3D221136078.1398283072.1.1.utmcsr%3D(direct)%7Cutmccn%3D(direct)%7Cutmcmd%3D(none)%3B&utmu=q~",
      "http://static.adzerk.net/ados.js",
      "http://static.adzerk.net/Advertisers/ea529209f3cf4623b79a2ad0d3a04a7c.png",
      "http://www.google-analytics.com/__utm.gif?utmwv=5.5.0&utms=1&utmn=1084152484&utmhn=gruntjs.com&utmcs=UTF-8&utmsr=1920x1080&utmvp=1280x1024&utmsc=32-bit&utmul=de-de&utmje=0&utmfl=-&utmdt=Grunt%3A%20The%20JavaScript%20Task%20Runner&utmhid=1565166529&utmr=-&utmp=%2F&utmht=1398283071785&utmac=UA-34623937-1&utmcc=__utma%3D221136078.349624065.1398283072.1398283072.1398283072.1%3B%2B__utmz%3D221136078.1398283072.1.1.utmcsr%3D(direct)%7Cutmccn%3D(direct)%7Cutmcmd%3D(none)%3B&utmu=q~",
      "http://static.adzerk.net/Advertisers/a315a7f3eb014d5f917e6aa646abf030.jpg",
      "http://www.google-analytics.com/__utm.gif?utmwv=5.5.0&utms=1&utmn=1305650803&utmhn=gruntjs.com&utmcs=UTF-8&utmsr=1920x1080&utmvp=1280x1024&utmsc=32-bit&utmul=de-de&utmje=0&utmfl=-&utmdt=Grunt%3A%20The%20JavaScript%20Task%20Runner&utmhid=1378832192&utmr=-&utmp=%2F&utmht=1398283070707&utmac=UA-34623937-1&utmcc=__utma%3D221136078.1153693557.1398283071.1398283071.1398283071.1%3B%2B__utmz%3D221136078.1398283071.1.1.utmcsr%3D(direct)%7Cutmccn%3D(direct)%7Cutmcmd%3D(none)%3B&utmu=q~",
      "http://static.adzerk.net/Advertisers/020dc19f551e443585f221f54eb94c4b.png",
      "http://www.google-analytics.com/__utm.gif?utmwv=5.5.0&utms=1&utmn=486959357&utmhn=gruntjs.com&utmcs=UTF-8&utmsr=1920x1080&utmvp=1280x1024&utmsc=32-bit&utmul=de-de&utmje=0&utmfl=-&utmdt=Grunt%3A%20The%20JavaScript%20Task%20Runner&utmhid=1175971230&utmr=-&utmp=%2F&utmht=1398283072222&utmac=UA-34623937-1&utmcc=__utma%3D221136078.648545905.1398283072.1398283072.1398283072.1%3B%2B__utmz%3D221136078.1398283072.1.1.utmcsr%3D(direct)%7Cutmccn%3D(direct)%7Cutmcmd%3D(none)%3B&utmu=q~",
      "http://www.google-analytics.com/__utm.gif?utmwv=5.5.0&utms=1&utmn=521956102&utmhn=gruntjs.com&utmcs=UTF-8&utmsr=1920x1080&utmvp=1280x1024&utmsc=32-bit&utmul=de-de&utmje=0&utmfl=-&utmdt=Grunt%3A%20The%20JavaScript%20Task%20Runner&utmhid=1117730328&utmr=-&utmp=%2F&utmht=1398283070900&utmac=UA-34623937-1&utmcc=__utma%3D221136078.1295273603.1398283071.1398283071.1398283071.1%3B%2B__utmz%3D221136078.1398283071.1.1.utmcsr%3D(direct)%7Cutmccn%3D(direct)%7Cutmcmd%3D(none)%3B&utmu=q~",
      "http://static.adzerk.net/Advertisers/327c84a8e1a64e36b74beeba7ec8a08b.jpg"
    ],
    "cachingNotSpecified": [
      "http://www.google-analytics.com/__utm.gif?utmwv=5.5.0&utms=1&utmn=365335679&utmhn=gruntjs.com&utmcs=UTF-8&utmsr=1920x1080&utmvp=2560x2048&utmsc=32-bit&utmul=de-de&utmje=0&utmfl=-&utmdt=Grunt%3A%20The%20JavaScript%20Task%20Runner&utmhid=1949298360&utmr=-&utmp=%2F&utmht=1398283071719&utmac=UA-34623937-1&utmcc=__utma%3D221136078.870192107.1398283072.1398283072.1398283072.1%3B%2B__utmz%3D221136078.1398283072.1.1.utmcsr%3D(direct)%7Cutmccn%3D(direct)%7Cutmcmd%3D(none)%3B&utmu=q~",
      "http://engine.adzerk.net/ados?t=1398283072066&request=%7B%22Placements%22:%5B%7B%22A%22:4433,%22S%22:27854,%22D%22:%22azk48893%22,%22AT%22:1%7D%5D,%22Keywords%22:%22undefined%22,%22Referrer%22:%22%22,%22IsAsync%22:true%7D",
      "http://static.adzerk.net/Advertisers/ea529209f3cf4623b79a2ad0d3a04a7c.png",
      "http://engine.adzerk.net/i.gif?e=eyJhdiI6MjAwNjksImF0IjoxLCJjbSI6MjgxMDEsImNoIjo2OTkyLCJjciI6MTQ5NTE5LCJkaSI6IjE2NWIzZWYzMWRkNjRmMDA5ZTkzMjhkZGFmYjlhMzJlIiwiZG0iOjEsImZjIjoyMDMxMDcsImZsIjo0Njk3Nywia3ciOiJ1bmRlZmluZWQiLCJudyI6NDQzMywicGMiOjAsInByIjoxNjI5MSwicnQiOjEsInN0IjoyNzg1NCwidHIiOnRydWUsInVrIjoidWUxLWJmN2UyNmFiM2E3NTQxZmU4ZDhlNjk3YzY4ZTUyNzAzIiwidHMiOjEzOTgyODMwOTQ5ODF9&s=0bGqzQjiXoYnoQDjbof1KZMtS_g",
      "http://www.google-analytics.com/__utm.gif?utmwv=5.5.0&utms=1&utmn=1084152484&utmhn=gruntjs.com&utmcs=UTF-8&utmsr=1920x1080&utmvp=1280x1024&utmsc=32-bit&utmul=de-de&utmje=0&utmfl=-&utmdt=Grunt%3A%20The%20JavaScript%20Task%20Runner&utmhid=1565166529&utmr=-&utmp=%2F&utmht=1398283071785&utmac=UA-34623937-1&utmcc=__utma%3D221136078.349624065.1398283072.1398283072.1398283072.1%3B%2B__utmz%3D221136078.1398283072.1.1.utmcsr%3D(direct)%7Cutmccn%3D(direct)%7Cutmcmd%3D(none)%3B&utmu=q~",
      "http://engine.adzerk.net/ados?t=1398283072019&request=%7B%22Placements%22:%5B%7B%22A%22:4433,%22S%22:27854,%22D%22:%22azk48893%22,%22AT%22:1%7D%5D,%22Keywords%22:%22undefined%22,%22Referrer%22:%22%22,%22IsAsync%22:true%7D",
      "http://engine.adzerk.net/i.gif?e=eyJhdiI6MjA3ODIsImF0IjoxLCJjbSI6MjkxNDIsImNoIjo2OTkyLCJjciI6NzAwMjQsImRpIjoiNzc1MmNjODc3OTk1NDNiMzg4NGJlNmI0YWFhNDcyMzYiLCJkbSI6MSwiZmMiOjk4MTk0LCJmbCI6NDg3OTEsImt3IjoidW5kZWZpbmVkIiwibnciOjQ0MzMsInBjIjowLCJwciI6MTYyOTEsInJ0IjoxLCJzdCI6Mjc4NTQsInVrIjoidWUxLTM2YjlmMzU4YzE1YTQ0YTI5Mjg4Zjc5NWY0Mzg0YjhhIiwidHMiOjEzOTgyODMxMTkxODZ9&s=u_-6631ZUDgB5aef2BawmZr15w0",
      "http://static.adzerk.net/Advertisers/a315a7f3eb014d5f917e6aa646abf030.jpg",
      "http://www.google-analytics.com/__utm.gif?utmwv=5.5.0&utms=1&utmn=1305650803&utmhn=gruntjs.com&utmcs=UTF-8&utmsr=1920x1080&utmvp=1280x1024&utmsc=32-bit&utmul=de-de&utmje=0&utmfl=-&utmdt=Grunt%3A%20The%20JavaScript%20Task%20Runner&utmhid=1378832192&utmr=-&utmp=%2F&utmht=1398283070707&utmac=UA-34623937-1&utmcc=__utma%3D221136078.1153693557.1398283071.1398283071.1398283071.1%3B%2B__utmz%3D221136078.1398283071.1.1.utmcsr%3D(direct)%7Cutmccn%3D(direct)%7Cutmcmd%3D(none)%3B&utmu=q~",
      "http://engine.adzerk.net/ados?t=1398283070583&request=%7B%22Placements%22:%5B%7B%22A%22:4433,%22S%22:27854,%22D%22:%22azk48893%22,%22AT%22:1%7D%5D,%22Keywords%22:%22undefined%22,%22Referrer%22:%22%22,%22IsAsync%22:true%7D",
      "http://engine.adzerk.net/i.gif?e=eyJhdiI6MjAwNjksImF0IjoxLCJjbSI6MjgxMDEsImNoIjo2OTkyLCJjciI6Mjc2NjA3LCJkaSI6ImQzZGIxYjZhNTIzYzQzZjE4MmZhYjkxMzAwYmIwMDM5IiwiZG0iOjEsImZjIjozNDE5OTYsImZsIjo0Njk3Nywia3ciOiJ1bmRlZmluZWQiLCJudyI6NDQzMywicGMiOjAsInByIjoxNjI5MSwicnQiOjEsInN0IjoyNzg1NCwidHIiOnRydWUsInVrIjoidWUxLTExYjUwZmU4ZjY5NDQxYjlhNzU2NTJhYzY4ZWM0ZDk1IiwidHMiOjEzOTgyODMxMDUwMzF9&s=HqmSw42vH7iiBNY9jVYMMY-CdVI",
      "http://static.adzerk.net/Advertisers/020dc19f551e443585f221f54eb94c4b.png",
      "http://www.google-analytics.com/__utm.gif?utmwv=5.5.0&utms=1&utmn=486959357&utmhn=gruntjs.com&utmcs=UTF-8&utmsr=1920x1080&utmvp=1280x1024&utmsc=32-bit&utmul=de-de&utmje=0&utmfl=-&utmdt=Grunt%3A%20The%20JavaScript%20Task%20Runner&utmhid=1175971230&utmr=-&utmp=%2F&utmht=1398283072222&utmac=UA-34623937-1&utmcc=__utma%3D221136078.648545905.1398283072.1398283072.1398283072.1%3B%2B__utmz%3D221136078.1398283072.1.1.utmcsr%3D(direct)%7Cutmccn%3D(direct)%7Cutmcmd%3D(none)%3B&utmu=q~",
      "http://engine.adzerk.net/ados?t=1398283072092&request=%7B%22Placements%22:%5B%7B%22A%22:4433,%22S%22:27854,%22D%22:%22azk48893%22,%22AT%22:1%7D%5D,%22Keywords%22:%22undefined%22,%22Referrer%22:%22%22,%22IsAsync%22:true%7D",
      "http://engine.adzerk.net/i.gif?e=eyJhdiI6MjA3ODIsImF0IjoxLCJjbSI6MjkxNDIsImNoIjo2OTkyLCJjciI6NzAwMjQsImRpIjoiYTQzMDRhZDY4ODQyNDAyYmIzMDA3YTU4ODZlYTRlOWMiLCJkbSI6MSwiZmMiOjk4MTk0LCJmbCI6NDg3OTEsImt3IjoidW5kZWZpbmVkIiwibnciOjQ0MzMsInBjIjowLCJwciI6MTYyOTEsInJ0IjoxLCJzdCI6Mjc4NTQsInVrIjoidWUxLTBkZDI1OTUwODE5YjQzMjA5YzEzNjk2YzQ0YjU1NDY4IiwidHMiOjEzOTgyODMwNzUwNDR9&s=5o_X5iGloDwHyZZwKCR0s2s5vkY",
      "http://www.google-analytics.com/__utm.gif?utmwv=5.5.0&utms=1&utmn=521956102&utmhn=gruntjs.com&utmcs=UTF-8&utmsr=1920x1080&utmvp=1280x1024&utmsc=32-bit&utmul=de-de&utmje=0&utmfl=-&utmdt=Grunt%3A%20The%20JavaScript%20Task%20Runner&utmhid=1117730328&utmr=-&utmp=%2F&utmht=1398283070900&utmac=UA-34623937-1&utmcc=__utma%3D221136078.1295273603.1398283071.1398283071.1398283071.1%3B%2B__utmz%3D221136078.1398283071.1.1.utmcsr%3D(direct)%7Cutmccn%3D(direct)%7Cutmcmd%3D(none)%3B&utmu=q~",
      "http://engine.adzerk.net/ados?t=1398283070593&request=%7B%22Placements%22:%5B%7B%22A%22:4433,%22S%22:27854,%22D%22:%22azk48893%22,%22AT%22:1%7D%5D,%22Keywords%22:%22undefined%22,%22Referrer%22:%22%22,%22IsAsync%22:true%7D",
      "http://engine.adzerk.net/i.gif?e=eyJhdiI6MjAwNjksImF0IjoxLCJjbSI6MjgxMDEsImNoIjo2OTkyLCJjciI6Njk4MDgsImRpIjoiZWUzNzc1NmQyNGQxNGRlY2FmMjJjOGRjYTQ5ZWFmZTQiLCJkbSI6MSwiZmMiOjk3Nzk3LCJmbCI6NDY5NzcsImt3IjoidW5kZWZpbmVkIiwibnciOjQ0MzMsInBjIjowLCJwciI6MTYyOTEsInJ0IjoxLCJzdCI6Mjc4NTQsInRyIjp0cnVlLCJ1ayI6InVlMS02NWEyYjNkZjM4MDQ0NWI1ODI4NzljNDdiNzhjNzVhZSIsInRzIjoxMzk4MjgzMTExMzUxfQ&s=h41rTyWaa6AKXjumf6GuC0DvlUk",
      "http://static.adzerk.net/Advertisers/327c84a8e1a64e36b74beeba7ec8a08b.jpg"
    ],
    "headersBiggerThanContent": [
      "http://www.google-analytics.com/__utm.gif?utmwv=5.5.0&utms=1&utmn=365335679&utmhn=gruntjs.com&utmcs=UTF-8&utmsr=1920x1080&utmvp=2560x2048&utmsc=32-bit&utmul=de-de&utmje=0&utmfl=-&utmdt=Grunt%3A%20The%20JavaScript%20Task%20Runner&utmhid=1949298360&utmr=-&utmp=%2F&utmht=1398283071719&utmac=UA-34623937-1&utmcc=__utma%3D221136078.870192107.1398283072.1398283072.1398283072.1%3B%2B__utmz%3D221136078.1398283072.1.1.utmcsr%3D(direct)%7Cutmccn%3D(direct)%7Cutmcmd%3D(none)%3B&utmu=q~ (body: 0.03 kB / headers: 0.34 kB)",
      "http://engine.adzerk.net/i.gif?e=eyJhdiI6MjAwNjksImF0IjoxLCJjbSI6MjgxMDEsImNoIjo2OTkyLCJjciI6MTQ5NTE5LCJkaSI6IjE2NWIzZWYzMWRkNjRmMDA5ZTkzMjhkZGFmYjlhMzJlIiwiZG0iOjEsImZjIjoyMDMxMDcsImZsIjo0Njk3Nywia3ciOiJ1bmRlZmluZWQiLCJudyI6NDQzMywicGMiOjAsInByIjoxNjI5MSwicnQiOjEsInN0IjoyNzg1NCwidHIiOnRydWUsInVrIjoidWUxLWJmN2UyNmFiM2E3NTQxZmU4ZDhlNjk3YzY4ZTUyNzAzIiwidHMiOjEzOTgyODMwOTQ5ODF9&s=0bGqzQjiXoYnoQDjbof1KZMtS_g (body: 0.04 kB / headers: 0.91 kB)",
      "http://www.google-analytics.com/__utm.gif?utmwv=5.5.0&utms=1&utmn=1084152484&utmhn=gruntjs.com&utmcs=UTF-8&utmsr=1920x1080&utmvp=1280x1024&utmsc=32-bit&utmul=de-de&utmje=0&utmfl=-&utmdt=Grunt%3A%20The%20JavaScript%20Task%20Runner&utmhid=1565166529&utmr=-&utmp=%2F&utmht=1398283071785&utmac=UA-34623937-1&utmcc=__utma%3D221136078.349624065.1398283072.1398283072.1398283072.1%3B%2B__utmz%3D221136078.1398283072.1.1.utmcsr%3D(direct)%7Cutmccn%3D(direct)%7Cutmcmd%3D(none)%3B&utmu=q~ (body: 0.03 kB / headers: 0.34 kB)",
      "http://engine.adzerk.net/i.gif?e=eyJhdiI6MjA3ODIsImF0IjoxLCJjbSI6MjkxNDIsImNoIjo2OTkyLCJjciI6NzAwMjQsImRpIjoiNzc1MmNjODc3OTk1NDNiMzg4NGJlNmI0YWFhNDcyMzYiLCJkbSI6MSwiZmMiOjk4MTk0LCJmbCI6NDg3OTEsImt3IjoidW5kZWZpbmVkIiwibnciOjQ0MzMsInBjIjowLCJwciI6MTYyOTEsInJ0IjoxLCJzdCI6Mjc4NTQsInVrIjoidWUxLTM2YjlmMzU4YzE1YTQ0YTI5Mjg4Zjc5NWY0Mzg0YjhhIiwidHMiOjEzOTgyODMxMTkxODZ9&s=u_-6631ZUDgB5aef2BawmZr15w0 (body: 0.04 kB / headers: 0.45 kB)",
      "http://www.google-analytics.com/__utm.gif?utmwv=5.5.0&utms=1&utmn=1305650803&utmhn=gruntjs.com&utmcs=UTF-8&utmsr=1920x1080&utmvp=1280x1024&utmsc=32-bit&utmul=de-de&utmje=0&utmfl=-&utmdt=Grunt%3A%20The%20JavaScript%20Task%20Runner&utmhid=1378832192&utmr=-&utmp=%2F&utmht=1398283070707&utmac=UA-34623937-1&utmcc=__utma%3D221136078.1153693557.1398283071.1398283071.1398283071.1%3B%2B__utmz%3D221136078.1398283071.1.1.utmcsr%3D(direct)%7Cutmccn%3D(direct)%7Cutmcmd%3D(none)%3B&utmu=q~ (body: 0.03 kB / headers: 0.34 kB)",
      "http://engine.adzerk.net/i.gif?e=eyJhdiI6MjAwNjksImF0IjoxLCJjbSI6MjgxMDEsImNoIjo2OTkyLCJjciI6Mjc2NjA3LCJkaSI6ImQzZGIxYjZhNTIzYzQzZjE4MmZhYjkxMzAwYmIwMDM5IiwiZG0iOjEsImZjIjozNDE5OTYsImZsIjo0Njk3Nywia3ciOiJ1bmRlZmluZWQiLCJudyI6NDQzMywicGMiOjAsInByIjoxNjI5MSwicnQiOjEsInN0IjoyNzg1NCwidHIiOnRydWUsInVrIjoidWUxLTExYjUwZmU4ZjY5NDQxYjlhNzU2NTJhYzY4ZWM0ZDk1IiwidHMiOjEzOTgyODMxMDUwMzF9&s=HqmSw42vH7iiBNY9jVYMMY-CdVI (body: 0.04 kB / headers: 0.91 kB)",
      "http://www.google-analytics.com/__utm.gif?utmwv=5.5.0&utms=1&utmn=486959357&utmhn=gruntjs.com&utmcs=UTF-8&utmsr=1920x1080&utmvp=1280x1024&utmsc=32-bit&utmul=de-de&utmje=0&utmfl=-&utmdt=Grunt%3A%20The%20JavaScript%20Task%20Runner&utmhid=1175971230&utmr=-&utmp=%2F&utmht=1398283072222&utmac=UA-34623937-1&utmcc=__utma%3D221136078.648545905.1398283072.1398283072.1398283072.1%3B%2B__utmz%3D221136078.1398283072.1.1.utmcsr%3D(direct)%7Cutmccn%3D(direct)%7Cutmcmd%3D(none)%3B&utmu=q~ (body: 0.03 kB / headers: 0.34 kB)",
      "http://engine.adzerk.net/i.gif?e=eyJhdiI6MjA3ODIsImF0IjoxLCJjbSI6MjkxNDIsImNoIjo2OTkyLCJjciI6NzAwMjQsImRpIjoiYTQzMDRhZDY4ODQyNDAyYmIzMDA3YTU4ODZlYTRlOWMiLCJkbSI6MSwiZmMiOjk4MTk0LCJmbCI6NDg3OTEsImt3IjoidW5kZWZpbmVkIiwibnciOjQ0MzMsInBjIjowLCJwciI6MTYyOTEsInJ0IjoxLCJzdCI6Mjc4NTQsInVrIjoidWUxLTBkZDI1OTUwODE5YjQzMjA5YzEzNjk2YzQ0YjU1NDY4IiwidHMiOjEzOTgyODMwNzUwNDR9&s=5o_X5iGloDwHyZZwKCR0s2s5vkY (body: 0.04 kB / headers: 0.45 kB)",
      "http://www.google-analytics.com/__utm.gif?utmwv=5.5.0&utms=1&utmn=521956102&utmhn=gruntjs.com&utmcs=UTF-8&utmsr=1920x1080&utmvp=1280x1024&utmsc=32-bit&utmul=de-de&utmje=0&utmfl=-&utmdt=Grunt%3A%20The%20JavaScript%20Task%20Runner&utmhid=1117730328&utmr=-&utmp=%2F&utmht=1398283070900&utmac=UA-34623937-1&utmcc=__utma%3D221136078.1295273603.1398283071.1398283071.1398283071.1%3B%2B__utmz%3D221136078.1398283071.1.1.utmcsr%3D(direct)%7Cutmccn%3D(direct)%7Cutmcmd%3D(none)%3B&utmu=q~ (body: 0.03 kB / headers: 0.34 kB)",
      "http://engine.adzerk.net/i.gif?e=eyJhdiI6MjAwNjksImF0IjoxLCJjbSI6MjgxMDEsImNoIjo2OTkyLCJjciI6Njk4MDgsImRpIjoiZWUzNzc1NmQyNGQxNGRlY2FmMjJjOGRjYTQ5ZWFmZTQiLCJkbSI6MSwiZmMiOjk3Nzk3LCJmbCI6NDY5NzcsImt3IjoidW5kZWZpbmVkIiwibnciOjQ0MzMsInBjIjowLCJwciI6MTYyOTEsInJ0IjoxLCJzdCI6Mjc4NTQsInRyIjp0cnVlLCJ1ayI6InVlMS02NWEyYjNkZjM4MDQ0NWI1ODI4NzljNDdiNzhjNzVhZSIsInRzIjoxMzk4MjgzMTExMzUxfQ&s=h41rTyWaa6AKXjumf6GuC0DvlUk (body: 0.04 kB / headers: 0.91 kB)"
    ],
    "smallImages": [
      "http://engine.adzerk.net/i.gif?e=eyJhdiI6MjAwNjksImF0IjoxLCJjbSI6MjgxMDEsImNoIjo2OTkyLCJjciI6MTQ5NTE5LCJkaSI6IjE2NWIzZWYzMWRkNjRmMDA5ZTkzMjhkZGFmYjlhMzJlIiwiZG0iOjEsImZjIjoyMDMxMDcsImZsIjo0Njk3Nywia3ciOiJ1bmRlZmluZWQiLCJudyI6NDQzMywicGMiOjAsInByIjoxNjI5MSwicnQiOjEsInN0IjoyNzg1NCwidHIiOnRydWUsInVrIjoidWUxLWJmN2UyNmFiM2E3NTQxZmU4ZDhlNjk3YzY4ZTUyNzAzIiwidHMiOjEzOTgyODMwOTQ5ODF9&s=0bGqzQjiXoYnoQDjbof1KZMtS_g (0.04 kB)",
      "http://engine.adzerk.net/i.gif?e=eyJhdiI6MjA3ODIsImF0IjoxLCJjbSI6MjkxNDIsImNoIjo2OTkyLCJjciI6NzAwMjQsImRpIjoiNzc1MmNjODc3OTk1NDNiMzg4NGJlNmI0YWFhNDcyMzYiLCJkbSI6MSwiZmMiOjk4MTk0LCJmbCI6NDg3OTEsImt3IjoidW5kZWZpbmVkIiwibnciOjQ0MzMsInBjIjowLCJwciI6MTYyOTEsInJ0IjoxLCJzdCI6Mjc4NTQsInVrIjoidWUxLTM2YjlmMzU4YzE1YTQ0YTI5Mjg4Zjc5NWY0Mzg0YjhhIiwidHMiOjEzOTgyODMxMTkxODZ9&s=u_-6631ZUDgB5aef2BawmZr15w0 (0.04 kB)",
      "http://engine.adzerk.net/i.gif?e=eyJhdiI6MjAwNjksImF0IjoxLCJjbSI6MjgxMDEsImNoIjo2OTkyLCJjciI6Mjc2NjA3LCJkaSI6ImQzZGIxYjZhNTIzYzQzZjE4MmZhYjkxMzAwYmIwMDM5IiwiZG0iOjEsImZjIjozNDE5OTYsImZsIjo0Njk3Nywia3ciOiJ1bmRlZmluZWQiLCJudyI6NDQzMywicGMiOjAsInByIjoxNjI5MSwicnQiOjEsInN0IjoyNzg1NCwidHIiOnRydWUsInVrIjoidWUxLTExYjUwZmU4ZjY5NDQxYjlhNzU2NTJhYzY4ZWM0ZDk1IiwidHMiOjEzOTgyODMxMDUwMzF9&s=HqmSw42vH7iiBNY9jVYMMY-CdVI (0.04 kB)",
      "http://engine.adzerk.net/i.gif?e=eyJhdiI6MjA3ODIsImF0IjoxLCJjbSI6MjkxNDIsImNoIjo2OTkyLCJjciI6NzAwMjQsImRpIjoiYTQzMDRhZDY4ODQyNDAyYmIzMDA3YTU4ODZlYTRlOWMiLCJkbSI6MSwiZmMiOjk4MTk0LCJmbCI6NDg3OTEsImt3IjoidW5kZWZpbmVkIiwibnciOjQ0MzMsInBjIjowLCJwciI6MTYyOTEsInJ0IjoxLCJzdCI6Mjc4NTQsInVrIjoidWUxLTBkZDI1OTUwODE5YjQzMjA5YzEzNjk2YzQ0YjU1NDY4IiwidHMiOjEzOTgyODMwNzUwNDR9&s=5o_X5iGloDwHyZZwKCR0s2s5vkY (0.04 kB)",
      "http://engine.adzerk.net/i.gif?e=eyJhdiI6MjAwNjksImF0IjoxLCJjbSI6MjgxMDEsImNoIjo2OTkyLCJjciI6Njk4MDgsImRpIjoiZWUzNzc1NmQyNGQxNGRlY2FmMjJjOGRjYTQ5ZWFmZTQiLCJkbSI6MSwiZmMiOjk3Nzk3LCJmbCI6NDY5NzcsImt3IjoidW5kZWZpbmVkIiwibnciOjQ0MzMsInBjIjowLCJwciI6MTYyOTEsInJ0IjoxLCJzdCI6Mjc4NTQsInRyIjp0cnVlLCJ1ayI6InVlMS02NWEyYjNkZjM4MDQ0NWI1ODI4NzljNDdiNzhjNzVhZSIsInRzIjoxMzk4MjgzMTExMzUxfQ&s=h41rTyWaa6AKXjumf6GuC0DvlUk (0.04 kB)"
    ],
    "domains": [
      "gruntjs.com: 21 request(s)",
      "www.google-analytics.com: 2 request(s)",
      "static.adzerk.net: 2 request(s)",
      "engine.adzerk.net: 2 request(s)",
      "fonts.googleapis.com: 1 request(s)"
    ],
    "imagesWithoutDimensions": [
      "body > div.content > div.container > div.row-fluid > div.span9.page > div.hero-unit > div.technology > div[2] > a.technology > span.logo > img[0]",
      "body > div.content > div.container > div.row-fluid > div.span9.page > div.hero-unit > div.who-uses-grunt > div[2] > a.technology > span.logo > img[0]"
    ],
    "DOMqueries": [
      "id \"#azk48893\": 4 queries",
      "tag name \"script\": 3 queries"
    ],
    "globalVariables": [
      "azk48893_html_94456",
      "azk48893_pixel_12749",
      "p",
      "_gaq",
      "z",
      "ados",
      "azk48893_pixel_command_88236",
      "d",
      "azk48893_html_command_36523",
      "s",
      "html5",
      "Modernizr",
      "_gat",
      "gaGlobal",
      "adosRun",
      "cssLoad",
      "cssLinkLoad",
      "azHtmlLoad",
      "azScriptSRCLoad",
      "azScriptExtensionLoad",
      "azRegisterExtension",
      "azInitExtension",
      "ados_async_load",
      "azScriptInlineLoad",
      "azLoad",
      "zshow",
      "ados_addInlinePlacement",
      "ados_add_placement",
      "ados_addPlacement",
      "ados_loadDiv",
      "ados_setKeywords",
      "ados_setKeywordCookie",
      "ados_setNoTrack",
      "ados_setDomain",
      "ados_setWriteResults",
      "ados_log",
      "ados_addPlacementObject",
      "ados_refresh",
      "ados_loadResults",
      "ados_load",
      "ados_loadInline",
      "ados_loadPassback",
      "ados_passback_next",
      "ados_findPassback",
      "ados_passback",
      "ados_execPassback",
      "ados_timeoutExpired",
      "ados_frameLoaded",
      "ados_passbackFilled",
      "ados_passbackWritePixel",
      "ados_writePixel",
      "ados_loadFIframe",
      "ados_passback_receiveMessage",
      "zItems",
      "adosResults",
      "azk48893_pixel_98703",
      "azk48893_html_command_13718",
      "azk48893_pixel_command_88016",
      "azk48893_html_32583",
      "azk48893_pixel_73880",
      "azk48893_pixel_command_45573",
      "azk48893_html_68206",
      "azk48893_html_command_42536",
      "azk48893_html_command_72817",
      "azk48893_pixel_12206",
      "azk48893_html_71713",
      "azk48893_pixel_command_54799",
      "azk48893_html_command_36844",
      "azk48893_html_55802",
      "azk48893_pixel_15561",
      "azk48893_pixel_command_15857"
    ],
    "smallestResponse": [
      "http://www.google-analytics.com/__utm.gif?utmwv=5.5.0&utms=1&utmn=365335679&utmhn=gruntjs.com&utmcs=UTF-8&utmsr=1920x1080&utmvp=2560x2048&utmsc=32-bit&utmul=de-de&utmje=0&utmfl=-&utmdt=Grunt%3A%20The%20JavaScript%20Task%20Runner&utmhid=1949298360&utmr=-&utmp=%2F&utmht=1398283071719&utmac=UA-34623937-1&utmcc=__utma%3D221136078.870192107.1398283072.1398283072.1398283072.1%3B%2B__utmz%3D221136078.1398283072.1.1.utmcsr%3D(direct)%7Cutmccn%3D(direct)%7Cutmcmd%3D(none)%3B&utmu=q~ (0.03 kB)",
      "http://www.google-analytics.com/__utm.gif?utmwv=5.5.0&utms=1&utmn=1084152484&utmhn=gruntjs.com&utmcs=UTF-8&utmsr=1920x1080&utmvp=1280x1024&utmsc=32-bit&utmul=de-de&utmje=0&utmfl=-&utmdt=Grunt%3A%20The%20JavaScript%20Task%20Runner&utmhid=1565166529&utmr=-&utmp=%2F&utmht=1398283071785&utmac=UA-34623937-1&utmcc=__utma%3D221136078.349624065.1398283072.1398283072.1398283072.1%3B%2B__utmz%3D221136078.1398283072.1.1.utmcsr%3D(direct)%7Cutmccn%3D(direct)%7Cutmcmd%3D(none)%3B&utmu=q~ (0.03 kB)",
      "http://www.google-analytics.com/__utm.gif?utmwv=5.5.0&utms=1&utmn=1305650803&utmhn=gruntjs.com&utmcs=UTF-8&utmsr=1920x1080&utmvp=1280x1024&utmsc=32-bit&utmul=de-de&utmje=0&utmfl=-&utmdt=Grunt%3A%20The%20JavaScript%20Task%20Runner&utmhid=1378832192&utmr=-&utmp=%2F&utmht=1398283070707&utmac=UA-34623937-1&utmcc=__utma%3D221136078.1153693557.1398283071.1398283071.1398283071.1%3B%2B__utmz%3D221136078.1398283071.1.1.utmcsr%3D(direct)%7Cutmccn%3D(direct)%7Cutmcmd%3D(none)%3B&utmu=q~ (0.03 kB)",
      "http://www.google-analytics.com/__utm.gif?utmwv=5.5.0&utms=1&utmn=486959357&utmhn=gruntjs.com&utmcs=UTF-8&utmsr=1920x1080&utmvp=1280x1024&utmsc=32-bit&utmul=de-de&utmje=0&utmfl=-&utmdt=Grunt%3A%20The%20JavaScript%20Task%20Runner&utmhid=1175971230&utmr=-&utmp=%2F&utmht=1398283072222&utmac=UA-34623937-1&utmcc=__utma%3D221136078.648545905.1398283072.1398283072.1398283072.1%3B%2B__utmz%3D221136078.1398283072.1.1.utmcsr%3D(direct)%7Cutmccn%3D(direct)%7Cutmcmd%3D(none)%3B&utmu=q~ (0.03 kB)",
      "http://www.google-analytics.com/__utm.gif?utmwv=5.5.0&utms=1&utmn=521956102&utmhn=gruntjs.com&utmcs=UTF-8&utmsr=1920x1080&utmvp=1280x1024&utmsc=32-bit&utmul=de-de&utmje=0&utmfl=-&utmdt=Grunt%3A%20The%20JavaScript%20Task%20Runner&utmhid=1117730328&utmr=-&utmp=%2F&utmht=1398283070900&utmac=UA-34623937-1&utmcc=__utma%3D221136078.1295273603.1398283071.1398283071.1398283071.1%3B%2B__utmz%3D221136078.1398283071.1.1.utmcsr%3D(direct)%7Cutmccn%3D(direct)%7Cutmcmd%3D(none)%3B&utmu=q~ (0.03 kB)"
    ],
    "biggestResponse": [
      "http://gruntjs.com/css/main.css (92.89 kB)"
    ],
    "fastestResponse": [
      "http://www.google-analytics.com/__utm.gif?utmwv=5.5.0&utms=1&utmn=365335679&utmhn=gruntjs.com&utmcs=UTF-8&utmsr=1920x1080&utmvp=2560x2048&utmsc=32-bit&utmul=de-de&utmje=0&utmfl=-&utmdt=Grunt%3A%20The%20JavaScript%20Task%20Runner&utmhid=1949298360&utmr=-&utmp=%2F&utmht=1398283071719&utmac=UA-34623937-1&utmcc=__utma%3D221136078.870192107.1398283072.1398283072.1398283072.1%3B%2B__utmz%3D221136078.1398283072.1.1.utmcsr%3D(direct)%7Cutmccn%3D(direct)%7Cutmcmd%3D(none)%3B&utmu=q~ (58 ms)",
      "http://www.google-analytics.com/__utm.gif?utmwv=5.5.0&utms=1&utmn=1084152484&utmhn=gruntjs.com&utmcs=UTF-8&utmsr=1920x1080&utmvp=1280x1024&utmsc=32-bit&utmul=de-de&utmje=0&utmfl=-&utmdt=Grunt%3A%20The%20JavaScript%20Task%20Runner&utmhid=1565166529&utmr=-&utmp=%2F&utmht=1398283071785&utmac=UA-34623937-1&utmcc=__utma%3D221136078.349624065.1398283072.1398283072.1398283072.1%3B%2B__utmz%3D221136078.1398283072.1.1.utmcsr%3D(direct)%7Cutmccn%3D(direct)%7Cutmcmd%3D(none)%3B&utmu=q~ (38 ms)",
      "http://fonts.googleapis.com/css?family=Lato:400,700 (102 ms)",
      "http://www.google-analytics.com/__utm.gif?utmwv=5.5.0&utms=1&utmn=486959357&utmhn=gruntjs.com&utmcs=UTF-8&utmsr=1920x1080&utmvp=1280x1024&utmsc=32-bit&utmul=de-de&utmje=0&utmfl=-&utmdt=Grunt%3A%20The%20JavaScript%20Task%20Runner&utmhid=1175971230&utmr=-&utmp=%2F&utmht=1398283072222&utmac=UA-34623937-1&utmcc=__utma%3D221136078.648545905.1398283072.1398283072.1398283072.1%3B%2B__utmz%3D221136078.1398283072.1.1.utmcsr%3D(direct)%7Cutmccn%3D(direct)%7Cutmcmd%3D(none)%3B&utmu=q~ (41 ms)",
      "http://static.adzerk.net/ados.js (97 ms)"
    ],
    "slowestResponse": [
      "http://gruntjs.com/img/logo-fg.jpg (2205 ms)",
      "http://gruntjs.com/img/logo-requirejs.jpg (1669 ms)",
      "http://gruntjs.com/img/grunt-logo.svg (2066 ms)",
      "http://gruntjs.com/img/logo-bocoup.jpg (2331 ms)",
      "http://gruntjs.com/img/logo-saucelabs.jpg (2131 ms)"
    ],
    "smallestLatency": [
      "http://www.google-analytics.com/__utm.gif?utmwv=5.5.0&utms=1&utmn=365335679&utmhn=gruntjs.com&utmcs=UTF-8&utmsr=1920x1080&utmvp=2560x2048&utmsc=32-bit&utmul=de-de&utmje=0&utmfl=-&utmdt=Grunt%3A%20The%20JavaScript%20Task%20Runner&utmhid=1949298360&utmr=-&utmp=%2F&utmht=1398283071719&utmac=UA-34623937-1&utmcc=__utma%3D221136078.870192107.1398283072.1398283072.1398283072.1%3B%2B__utmz%3D221136078.1398283072.1.1.utmcsr%3D(direct)%7Cutmccn%3D(direct)%7Cutmcmd%3D(none)%3B&utmu=q~ (58 ms)",
      "http://www.google-analytics.com/__utm.gif?utmwv=5.5.0&utms=1&utmn=1084152484&utmhn=gruntjs.com&utmcs=UTF-8&utmsr=1920x1080&utmvp=1280x1024&utmsc=32-bit&utmul=de-de&utmje=0&utmfl=-&utmdt=Grunt%3A%20The%20JavaScript%20Task%20Runner&utmhid=1565166529&utmr=-&utmp=%2F&utmht=1398283071785&utmac=UA-34623937-1&utmcc=__utma%3D221136078.349624065.1398283072.1398283072.1398283072.1%3B%2B__utmz%3D221136078.1398283072.1.1.utmcsr%3D(direct)%7Cutmccn%3D(direct)%7Cutmcmd%3D(none)%3B&utmu=q~ (38 ms)",
      "http://fonts.googleapis.com/css?family=Lato:400,700 (102 ms)",
      "http://www.google-analytics.com/__utm.gif?utmwv=5.5.0&utms=1&utmn=486959357&utmhn=gruntjs.com&utmcs=UTF-8&utmsr=1920x1080&utmvp=1280x1024&utmsc=32-bit&utmul=de-de&utmje=0&utmfl=-&utmdt=Grunt%3A%20The%20JavaScript%20Task%20Runner&utmhid=1175971230&utmr=-&utmp=%2F&utmht=1398283072222&utmac=UA-34623937-1&utmcc=__utma%3D221136078.648545905.1398283072.1398283072.1398283072.1%3B%2B__utmz%3D221136078.1398283072.1.1.utmcsr%3D(direct)%7Cutmccn%3D(direct)%7Cutmcmd%3D(none)%3B&utmu=q~ (40 ms)",
      "http://static.adzerk.net/ados.js (97 ms)"
    ],
    "biggestLatency": [
      "http://gruntjs.com/img/logo-bocoup.jpg (1680 ms)",
      "http://gruntjs.com/img/logo-bitovi.jpg (1181 ms)",
      "http://gruntjs.com/img/logo-fg.jpg (1250 ms)",
      "http://gruntjs.com/img/logo-fg.jpg (1590 ms)",
      "http://gruntjs.com/img/logo-bocoup.jpg (1520 ms)"
    ]
  }
}